README.md
pyproject.toml
setup.py
gazpacho/__init__.py
gazpacho/get.py
gazpacho/py.typed
gazpacho/soup.py
gazpacho/utils.py
gazpacho.egg-info/PKG-INFO
gazpacho.egg-info/SOURCES.txt
gazpacho.egg-info/dependency_links.txt
gazpacho.egg-info/not-zip-safe
gazpacho.egg-info/requires.txt
gazpacho.egg-info/top_level.txt