Metadata-Version: 2.1
Name: gazpacho
Version: 1.1
Summary: The simple, fast, and modern web scraping library
Home-page: https://github.com/maxhumber/gazpacho
Author: Max Humber
Author-email: max.humber@gmail.com
License: MIT
Keywords: web scraping,BeautifulSoup,requests
Platform: UNKNOWN
Classifier: Development Status :: 5 - Production/Stable
Classifier: Intended Audience :: Developers
Classifier: License :: OSI Approved :: MIT License
Classifier: Natural Language :: English
Classifier: Programming Language :: Python :: 3
Classifier: Programming Language :: Python :: 3.6
Classifier: Programming Language :: Python :: 3.7
Classifier: Programming Language :: Python :: 3.8
Classifier: Programming Language :: Python :: 3.9
Requires-Python: >=3.6
Provides-Extra: dev
